{
  "project_info": {
    "project_number": "1047947161236",
    "project_id": "zezo-10aad",
    "storage_bucket": "zezo-10aad.firebasestorage.app"
  },
  "client": [
    {
      "client_info": {
        "mobilesdk_app_id": "1:1047947161236:android:301d5e787c94daa4344e81",
        "android_client_info": {
          "package_name": "com.example.firebase"
        }
      },
      "oauth_client": [],
      "api_key": [
        {
          "current_key": "AIzaSyCPqGGaz6ro9nnuVgI9k13Ca3e04ECASN4"
        }
      ],
      "services": {
        "appinvite_service": {
          "other_platform_oauth_client": []
        }
      }
    },
    {
      "client_info": {
        "mobilesdk_app_id": "1:1047947161236:android:bebdfb66b6c4c9e6344e81",
        "android_client_info": {
          "package_name": "com.example.fruits_app"
        }
      },
      "oauth_client": [],
      "api_key": [
        {
          "current_key": "AIzaSyCPqGGaz6ro9nnuVgI9k13Ca3e04ECASN4"
        }
      ],
      "services": {
        "appinvite_service": {
          "other_platform_oauth_client": []
        }
      }
    },
    {
      "client_info": {
        "mobilesdk_app_id": "1:1047947161236:android:3eab6b0351c88e66344e81",
        "android_client_info": {
          "package_name": "com.example.movie_app"
        }
      },
      "oauth_client": [],
      "api_key": [
        {
          "current_key": "AIzaSyCPqGGaz6ro9nnuVgI9k13Ca3e04ECASN4"
        }
      ],
      "services": {
        "appinvite_service": {
          "other_platform_oauth_client": []
        }
      }
    },
    {
      "client_info": {
        "mobilesdk_app_id": "1:1047947161236:android:be96c41e7192e16d344e81",
        "android_client_info": {
          "package_name": "com.example.todo_app"
        }
      },
      "oauth_client": [],
      "api_key": [
        {
          "current_key": "AIzaSyCPqGGaz6ro9nnuVgI9k13Ca3e04ECASN4"
        }
      ],
      "services": {
        "appinvite_service": {
          "other_platform_oauth_client": []
        }
      }
    },
    {
      "client_info": {
        "mobilesdk_app_id": "1:1047947161236:android:4acf664031f330e3344e81",
        "android_client_info": {
          "package_name": "com.zezo.chatApp"
        }
      },
      "oauth_client": [],
      "api_key": [
        {
          "current_key": "AIzaSyCPqGGaz6ro9nnuVgI9k13Ca3e04ECASN4"
        }
      ],
      "services": {
        "appinvite_service": {
          "other_platform_oauth_client": []
        }
      }
    }
  ],
  "configuration_version": "1"
}